[
  {
    "eventId": "EVT001",
    "title": "TechFusion Hackathon 2026",
    "description": "24-hour hackathon open to all departments. Build innovative solutions.",
    "date": "2026-03-15",
    "time": "09:00 AM",
    "venue": "Main Auditorium",
    "organizer": "CSE Department",
    "category": "Technical",
    "registrationDeadline": "2026-03-10",
    "maxParticipants": 200,
    "registeredCount": 142,
    "status": "upcoming"
  },
  {
    "eventId": "EVT002",
    "title": "Annual Sports Day",
    "description": "Inter-department sports competition featuring cricket, basketball, athletics.",
    "date": "2026-03-22",
    "time": "08:00 AM",
    "venue": "Sports Ground",
    "organizer": "Physical Education",
    "category": "Sports",
    "registrationDeadline": "2026-03-18",
    "maxParticipants": 500,
    "registeredCount": 310,
    "status": "upcoming"
  },
  {
    "eventId": "EVT003",
    "title": "Guest Lecture - AI in Healthcare",
    "description": "Talk by Dr. Priya Rajan from IIT Madras on AI applications in healthcare.",
    "date": "2026-04-05",
    "time": "02:00 PM",
    "venue": "Seminar Hall",
    "organizer": "CSE Department",
    "category": "Academic",
    "registrationDeadline": "2026-04-03",
    "maxParticipants": 150,
    "registeredCount": 87,
    "status": "upcoming"
  },
  {
    "eventId": "EVT004",
    "title": "Cultural Fest - Sangamam",
    "description": "Three-day cultural extravaganza with music, dance, drama, and art competitions.",
    "date": "2026-04-10",
    "time": "10:00 AM",
    "venue": "Campus Wide",
    "organizer": "Student Affairs",
    "category": "Cultural",
    "registrationDeadline": "2026-04-05",
    "maxParticipants": 1000,
    "registeredCount": 560,
    "status": "upcoming"
  },
  {
    "eventId": "EVT005",
    "title": "IoT Workshop",
    "description": "Hands-on workshop on Internet of Things with Arduino and Raspberry Pi.",
    "date": "2026-02-10",
    "time": "09:30 AM",
    "venue": "ECE Lab",
    "organizer": "ECE Department",
    "category": "Workshop",
    "maxParticipants": 60,
    "registeredCount": 58,
    "status": "completed"
  },
  {
    "eventId": "EVT006",
    "title": "Resume Building Seminar",
    "description": "Professional resume writing and interview skills workshop.",
    "date": "2026-02-05",
    "time": "11:00 AM",
    "venue": "Placement Cell",
    "organizer": "Training & Placement",
    "category": "Career",
    "maxParticipants": 200,
    "registeredCount": 175,
    "status": "completed"
  }
]